updes/__init__.py
updes/assembly.py
updes/cloud.py
updes/config.py
updes/operators.py
updes/utils.py
updes/visualise.py
updes-1.0.2.post1.dist-info/LICENSE
updes-1.0.2.post1.dist-info/METADATA
updes-1.0.2.post1.dist-info/WHEEL
updes-1.0.2.post1.dist-info/top_level.txt
updes-1.0.2.post1.dist-info/RECORD
