Metadata-Version: 2.1
Name: updes
Version: 1.0.2.post1
Summary: Universal Partial Differential Equations Simulator
Author-email: Roussel Desmond Nzoyem <desmond.ngueguin@gmail.com>
Project-URL: Homepage, https://github.com/ddrous/Updes
Project-URL: Documentation, https://ddrous.github.io/Updes/
Keywords: differentiable-programming,radial-basis-function,meshfree,optimisation,differentiable-physics,PDEs
License-File: LICENSE
Requires-Dist: jax >=0.3.4
Requires-Dist: lineax
Requires-Dist: gmsh
Requires-Dist: pytest
Requires-Dist: matplotlib >=3.4.0
Requires-Dist: scikit-learn
Requires-Dist: seaborn
Provides-Extra: dev
Requires-Dist: pyvista[trame] ; extra == 'dev'
Requires-Dist: quartodoc ; extra == 'dev'
